jinja_ab
