Metadata-Version: 1.1
Name: jinja-ab
Version: 0.3.0
Summary: Support A/B testing for Jinja2 templates
Home-page: https://github.com/MrSenko/jinja-ab
Author: Mr. Senko
Author-email: atodorov@mrsenko.com
License: BSD
Keywords: A/B testing,Jinja2
Platform: UNKNOWN
Classifier: Development Status :: 5 - Production/Stable
Classifier: Environment :: Web Environment
Classifier: Intended Audience :: Developers
Classifier: License :: OSI Approved :: BSD License
Classifier: Operating System :: OS Independent
Classifier: Programming Language :: Python
